multiuserfilelock/__init__.py
multiuserfilelock/_version.py
multiuserfilelock/tests/__init__.py
multiuserfilelock/tests/test_acquire.py
multiuserfilelock-0.0.10.dist-info/LICENSE
multiuserfilelock-0.0.10.dist-info/METADATA
multiuserfilelock-0.0.10.dist-info/WHEEL
multiuserfilelock-0.0.10.dist-info/top_level.txt
multiuserfilelock-0.0.10.dist-info/RECORD
