Metadata-Version: 2.1
Name: multiuserfilelock
Version: 0.0.10
Summary: A lock to share resources between users based on filelock.
Home-page: https://github.com/ramonaoptics/python-multiuserfilelock
Author: Ramona Optics, Inc.
Author-email: info@ramonaoptics.com
License: BSD
Classifier: Development Status :: 2 - Pre-Alpha
Classifier: Intended Audience :: Developers
Classifier: License :: OSI Approved :: BSD License
Classifier: Natural Language :: English
Classifier: Programming Language :: Python :: 3
Classifier: Programming Language :: Python :: 3.7
Classifier: Programming Language :: Python :: 3.8
Classifier: Programming Language :: Python :: 3.9
Classifier: Programming Language :: Python :: 3.10
Classifier: Programming Language :: Python :: 3.11
Classifier: Programming Language :: Python :: 3.12
Requires-Python: >=3.7
License-File: LICENSE
Requires-Dist: filelock!=3.11.0,!=3.13.0
